MANIFEST.in
README.txt
VERSION.txt
djangoaudit_nose.py
setup.cfg
setup.py
django_audit.egg-info/PKG-INFO
django_audit.egg-info/SOURCES.txt
django_audit.egg-info/dependency_links.txt
django_audit.egg-info/entry_points.txt
django_audit.egg-info/not-zip-safe
django_audit.egg-info/requires.txt
django_audit.egg-info/top_level.txt
djangoaudit/__init__.py
djangoaudit/connection.py
djangoaudit/forms.py
djangoaudit/models.py